crispy_bootstrap3/__init__.py
crispy_bootstrap3/templates/bootstrap3/accordion-group.html
crispy_bootstrap3/templates/bootstrap3/accordion.html
crispy_bootstrap3/templates/bootstrap3/betterform.html
crispy_bootstrap3/templates/bootstrap3/display_form.html
crispy_bootstrap3/templates/bootstrap3/errors.html
crispy_bootstrap3/templates/bootstrap3/errors_formset.html
crispy_bootstrap3/templates/bootstrap3/field.html
crispy_bootstrap3/templates/bootstrap3/inputs.html
crispy_bootstrap3/templates/bootstrap3/multifield.html
crispy_bootstrap3/templates/bootstrap3/table_inline_formset.html
crispy_bootstrap3/templates/bootstrap3/uni_form.html
crispy_bootstrap3/templates/bootstrap3/uni_formset.html
crispy_bootstrap3/templates/bootstrap3/whole_uni_form.html
crispy_bootstrap3/templates/bootstrap3/whole_uni_formset.html
crispy_bootstrap3/templates/bootstrap3/layout/alert.html
crispy_bootstrap3/templates/bootstrap3/layout/attrs.html
crispy_bootstrap3/templates/bootstrap3/layout/baseinput.html
crispy_bootstrap3/templates/bootstrap3/layout/button.html
crispy_bootstrap3/templates/bootstrap3/layout/buttonholder.html
crispy_bootstrap3/templates/bootstrap3/layout/checkboxselectmultiple.html
crispy_bootstrap3/templates/bootstrap3/layout/checkboxselectmultiple_inline.html
crispy_bootstrap3/templates/bootstrap3/layout/column.html
crispy_bootstrap3/templates/bootstrap3/layout/div.html
crispy_bootstrap3/templates/bootstrap3/layout/field_errors.html
crispy_bootstrap3/templates/bootstrap3/layout/field_errors_block.html
crispy_bootstrap3/templates/bootstrap3/layout/field_with_buttons.html
crispy_bootstrap3/templates/bootstrap3/layout/fieldset.html
crispy_bootstrap3/templates/bootstrap3/layout/formactions.html
crispy_bootstrap3/templates/bootstrap3/layout/help_text.html
crispy_bootstrap3/templates/bootstrap3/layout/help_text_and_errors.html
crispy_bootstrap3/templates/bootstrap3/layout/inline_field.html
crispy_bootstrap3/templates/bootstrap3/layout/modal.html
crispy_bootstrap3-2024.1.dist-info/LICENSE
crispy_bootstrap3-2024.1.dist-info/METADATA
crispy_bootstrap3-2024.1.dist-info/WHEEL
crispy_bootstrap3-2024.1.dist-info/top_level.txt
crispy_bootstrap3-2024.1.dist-info/RECORD
